shifucvefinder.py
shifucvefinder-1.0.0.dist-info/WHEEL
shifucvefinder-1.0.0.dist-info/METADATA
shifucvefinder-1.0.0.dist-info/RECORD
