Metadata-Version: 2.1
Name: shifucvefinder
Version: 1.0.0
Summary: SHIFU: CVE Finder Toolkit
Home-page: https://github.com/symbolexe/SHIFU
License: MIT
Author: Yasin Saffari
Author-email: symbolexe@proton.me
